CHANGES.rst
LICENSE
MANIFEST.in
README.rst
setup.py
sarah.egg-info/PKG-INFO
sarah.egg-info/SOURCES.txt
sarah.egg-info/dependency_links.txt
sarah.egg-info/not-zip-safe
sarah.egg-info/requires.txt
sarah.egg-info/top_level.txt
src/__init__.py
src/_itertools.py
src/_threading.py
src/cacheDecorators.py
src/coloredLogging.py
src/dictlike.py
src/drv.py
src/event.py
src/io.py
src/lazy.py
src/log.mirte
src/log.py
src/order.py
src/pack.py
src/refStore.mirte
src/refStore.py
src/runtime.py
src/scheduler.mirte
src/scheduler.py
src/selectPool.mirte
src/selectPool.py
src/shell.mirte
src/shell.py
src/socketServer.mirte
src/socketServer.py
src/string.py