Metadata-Version: 1.0
Name: sarah
Version: 0.1.4
Summary: Library with miscellaneous functionality
Home-page: http://github.com/bwesterb/sarah/
Author: Bas Westerbaan
Author-email: bas@westerbaan.name
License: UNKNOWN
Platform: UNKNOWN
